ehrapy/SCANPY_LICENSE
ehrapy/__init__.py
ehrapy/_compat.py
ehrapy/_progress.py
ehrapy/_settings.py
ehrapy/_types.py
ehrapy/_utils_doc.py
ehrapy/py.typed
ehrapy/anndata/__init__.py
ehrapy/anndata/_feature_specifications.py
ehrapy/anndata/anndata_ext.py
ehrapy/core/__init__.py
ehrapy/core/_constants.py
ehrapy/core/meta_information.py
ehrapy/data/__init__.py
ehrapy/data/_dataloader.py
ehrapy/data/_datasets.py
ehrapy/get/__init__.py
ehrapy/get/_get.py
ehrapy/io/__init__.py
ehrapy/io/_read.py
ehrapy/io/_write.py
ehrapy/plot/__init__.py
ehrapy/plot/_catplot.py
ehrapy/plot/_colormaps.py
ehrapy/plot/_missingno.py
ehrapy/plot/_sankey.py
ehrapy/plot/_scanpy_pl_api.py
ehrapy/plot/_survival_analysis.py
ehrapy/plot/_timeseries.py
ehrapy/plot/causal_inference/__init__.py
ehrapy/plot/causal_inference/_dowhy.py
ehrapy/plot/feature_ranking/__init__.py
ehrapy/plot/feature_ranking/_feature_importances.py
ehrapy/preprocessing/__init__.py
ehrapy/preprocessing/_balanced_sampling.py
ehrapy/preprocessing/_bias.py
ehrapy/preprocessing/_encoding.py
ehrapy/preprocessing/_filter.py
ehrapy/preprocessing/_highly_variable_features.py
ehrapy/preprocessing/_imputation.py
ehrapy/preprocessing/_neighbors.py
ehrapy/preprocessing/_normalization.py
ehrapy/preprocessing/_outliers.py
ehrapy/preprocessing/_quality_control.py
ehrapy/preprocessing/_scanpy_pp_api.py
ehrapy/preprocessing/_summarize_measurements.py
ehrapy/preprocessing/laboratory_reference_tables/laposata.tsv
ehrapy/tools/__init__.py
ehrapy/tools/_method_options.py
ehrapy/tools/_scanpy_tl_api.py
ehrapy/tools/_survival_analysis.py
ehrapy/tools/causal/__init__.py
ehrapy/tools/causal/_dowhy.py
ehrapy/tools/cohort_tracking/__init__.py
ehrapy/tools/cohort_tracking/_cohort_tracker.py
ehrapy/tools/distances/__init__.py
ehrapy/tools/distances/timeseries.py
ehrapy/tools/embedding/_embeddings.py
ehrapy/tools/feature_ranking/__init__.py
ehrapy/tools/feature_ranking/_feature_importances.py
ehrapy/tools/feature_ranking/_rank_features_groups.py
ehrapy-0.13.1.dist-info/METADATA
ehrapy-0.13.1.dist-info/WHEEL
ehrapy-0.13.1.dist-info/licenses/LICENSE
ehrapy-0.13.1.dist-info/RECORD
