Metadata-Version: 2.4
Name: ehrapy
Version: 0.13.1
Summary: Electronic Health Record Analysis with Python.
Project-URL: Documentation, https://ehrapy.readthedocs.io
Project-URL: Source, https://github.com/theislab/ehrapy
Project-URL: Home-page, https://github.com/theislab/ehrapy
Author: Lukas Heumos, Philipp Ehmele, Eljas Roellin, Lilly May, Tim Treis, Altana Namsaraeva, Vladimir Shitov, Luke Zappia, Xinyue Zhang
Maintainer-email: Lukas Heumos <lukas.heumos@posteo.net>
License: Apache License
License-File: LICENSE
Classifier: Development Status :: 4 - Beta
Classifier: Environment :: Console
Classifier: Framework :: Jupyter
Classifier: Intended Audience :: Developers
Classifier: Intended Audience :: Science/Research
Classifier: License :: OSI Approved :: Apache Software License
Classifier: Natural Language :: English
Classifier: Operating System :: MacOS :: MacOS X
Classifier: Operating System :: POSIX :: Linux
Classifier: Programming Language :: Python :: 3
Classifier: Programming Language :: Python :: 3.12
Classifier: Programming Language :: Python :: 3.13
Classifier: Programming Language :: Python :: 3.14
Classifier: Topic :: Scientific/Engineering :: Bio-Informatics
Classifier: Topic :: Scientific/Engineering :: Visualization
Requires-Python: <3.15,>=3.12
Requires-Dist: ehrdata
Requires-Dist: fast-array-utils[accel,sparse]
Requires-Dist: fhiry
Requires-Dist: filelock
Requires-Dist: fknni[faisscpu]>=1.3.0
Requires-Dist: holoviews[recommended]
Requires-Dist: igraph
Requires-Dist: lifelines>=0.30.0
Requires-Dist: miceforest
Requires-Dist: missingno
Requires-Dist: numba>=0.60.0
Requires-Dist: numpy>=2.0.0
Requires-Dist: pyampute
Requires-Dist: requests
Requires-Dist: scanpy
Requires-Dist: scikit-misc
Requires-Dist: tableone
Requires-Dist: thefuzz[speedup]
Requires-Dist: tslearn
Provides-Extra: causal
Requires-Dist: cvxpy>=1.7.3; extra == 'causal'
Requires-Dist: dowhy>=0.14; extra == 'causal'
Provides-Extra: dask
Requires-Dist: anndata[dask]; extra == 'dask'
Requires-Dist: dask-ml>=2025.1.0; extra == 'dask'
Provides-Extra: dev
Requires-Dist: pre-commit; extra == 'dev'
Provides-Extra: doc
Requires-Dist: anndata[dask]; extra == 'doc'
Requires-Dist: dask-ml>=2025.1.0; extra == 'doc'
Requires-Dist: docutils; extra == 'doc'
Requires-Dist: ipykernel; extra == 'doc'
Requires-Dist: ipython; extra == 'doc'
Requires-Dist: myst-nb; extra == 'doc'
Requires-Dist: myst-parser; extra == 'doc'
Requires-Dist: nbsphinx; extra == 'doc'
Requires-Dist: nbsphinx-link; extra == 'doc'
Requires-Dist: pygments; extra == 'doc'
Requires-Dist: scanpydoc; extra == 'doc'
Requires-Dist: sphinx; extra == 'doc'
Requires-Dist: sphinx-autodoc-typehints; extra == 'doc'
Requires-Dist: sphinx-automodapi; extra == 'doc'
Requires-Dist: sphinx-book-theme; extra == 'doc'
Requires-Dist: sphinx-copybutton; extra == 'doc'
Requires-Dist: sphinx-design; extra == 'doc'
Requires-Dist: sphinx-gallery; extra == 'doc'
Requires-Dist: sphinx-issues; extra == 'doc'
Requires-Dist: sphinx-last-updated-by-git; extra == 'doc'
Requires-Dist: sphinx-remove-toctrees; extra == 'doc'
Requires-Dist: sphinx-tabs; extra == 'doc'
Requires-Dist: sphinxcontrib-bibtex; extra == 'doc'
Requires-Dist: sphinxext-opengraph; extra == 'doc'
Provides-Extra: rapids12
Requires-Dist: rapids-singlecell[rapids12]; extra == 'rapids12'
Provides-Extra: rapids13
Requires-Dist: rapids-singlecell[rapids13]; extra == 'rapids13'
Provides-Extra: test
Requires-Dist: anndata[dask]; extra == 'test'
Requires-Dist: cvxpy>=1.7.3; extra == 'test'
Requires-Dist: dask-ml>=2025.1.0; extra == 'test'
Requires-Dist: dowhy>=0.14; extra == 'test'
Requires-Dist: pytest; extra == 'test'
Requires-Dist: pytest-cov; extra == 'test'
Requires-Dist: pytest-mock; extra == 'test'
